ffcut/__init__.py
ffcut/main.py
ffcut/test.py
ffcut-0.1.2.dist-info/DESCRIPTION.rst
ffcut-0.1.2.dist-info/METADATA
ffcut-0.1.2.dist-info/RECORD
ffcut-0.1.2.dist-info/WHEEL
ffcut-0.1.2.dist-info/entry_points.txt
ffcut-0.1.2.dist-info/metadata.json
ffcut-0.1.2.dist-info/pbr.json
ffcut-0.1.2.dist-info/top_level.txt
