Metadata-Version: 2.0
Name: ffcut
Version: 0.1.2
Summary: FFCut: Cutting Video with FFMpeg for Human Beings
Home-page: https://github.com/dtantsur/ffcut
Author: Dmitry Tantsur
Author-email: UNKNOWN
License: MIT
Platform: UNKNOWN
Classifier: Development Status :: 4 - Beta
Classifier: Environment :: Console
Classifier: Intended Audience :: End Users/Desktop
Classifier: License :: OSI Approved :: MIT License
Classifier: Operating System :: OS Independent
Classifier: Programming Language :: Python
Classifier: Programming Language :: Python :: 2
Classifier: Programming Language :: Python :: 2.7
Classifier: Programming Language :: Python :: 3
Classifier: Programming Language :: Python :: 3.5
Classifier: Topic :: Multimedia :: Video
